jsmon/__init__.py
jsmon/__main__.py
jsmon/cli.py
jsmon/analysis/__init__.py
jsmon/analysis/ai.py
jsmon/analysis/ai_providers.py
jsmon/analysis/debug_logger.py
jsmon/analysis/endpoints.py
jsmon/analysis/secrets.py
jsmon/analysis/smart_filters.py
jsmon/analysis/sourcemap.py
jsmon/analysis/trivia_filter.py
jsmon/config/__init__.py
jsmon/config/constants.py
jsmon/core/__init__.py
jsmon/core/crawler.py
jsmon/core/engine.py
jsmon/core/probing.py
jsmon/network/__init__.py
jsmon/network/browser.py
jsmon/network/fetcher.py
jsmon/network/headers.py
jsmon/network/timing.py
jsmon/network/waf.py
jsmon/reporting/__init__.py
jsmon/reporting/archive.py
jsmon/reporting/html_generator.py
jsmon/reporting/notifier.py
jsmon/reporting/templates.py
jsmon/storage/__init__.py
jsmon/storage/diff_storage.py
jsmon/storage/session.py
jsmon/utils/__init__.py
jsmon/utils/diff.py
jsmon/utils/hashing.py
jsmon/utils/url.py
jsmon-1.0.18.dist-info/licenses/LICENSE
jsmon-1.0.18.dist-info/METADATA
jsmon-1.0.18.dist-info/WHEEL
jsmon-1.0.18.dist-info/entry_points.txt
jsmon-1.0.18.dist-info/top_level.txt
jsmon-1.0.18.dist-info/RECORD
