Metadata-Version: 2.4
Name: jsmon
Version: 1.0.18
Summary: Advanced JavaScript monitoring for bug bounty hunters
Author-email: h3llwish <sosibonka3@gmail.com>
License-Expression: MIT
Project-URL: Homepage, https://github.com/h3llwish/jsmon
Project-URL: Documentation, https://github.com/h3llwish/jsmon
Project-URL: Repository, https://github.com/h3llwish/jsmon
Project-URL: Bug Tracker, https://github.com/h3llwish/jsmon/issues
Keywords: security,bug-bounty,javascript,monitoring,recon,pentesting
Classifier: Development Status :: 4 - Beta
Classifier: Intended Audience :: Information Technology
Classifier: Intended Audience :: Developers
Classifier: Programming Language :: Python :: 3
Classifier: Programming Language :: Python :: 3.8
Classifier: Programming Language :: Python :: 3.9
Classifier: Programming Language :: Python :: 3.10
Classifier: Programming Language :: Python :: 3.11
Classifier: Topic :: Security
Classifier: Topic :: Software Development :: Testing
Requires-Python: >=3.8
License-File: LICENSE
Requires-Dist: aiohttp>=3.8.0
Requires-Dist: redis>=4.5.0
Requires-Dist: playwright>=1.40.0
Requires-Dist: jsbeautifier>=1.14.0
Requires-Dist: beautifulsoup4>=4.11.0
Requires-Dist: lxml>=4.9.0
Requires-Dist: cryptography>=41.0.0
Requires-Dist: tqdm>=4.65.0
Requires-Dist: aiofiles>=23.0.0
Provides-Extra: dev
Requires-Dist: pytest>=7.0.0; extra == "dev"
Requires-Dist: pytest-asyncio>=0.21.0; extra == "dev"
Requires-Dist: black>=23.0.0; extra == "dev"
Requires-Dist: mypy>=1.0.0; extra == "dev"
Requires-Dist: pre-commit>=3.0.0; extra == "dev"
Dynamic: license-file
